Workbook

Sheet OnboardingTasks
A1: HR Onboarding Tasks — Daily Digest Agent
A2: Zapier reads this sheet every morning at 8am | Filter: Status = Open | Tab name must stay: OnboardingTasks
A3: TaskName | B3: AssigneeName | C3: AssigneeEmail | D3: DueDate | E3: Status | F3: Priority | G3: Department | H3: OnboardingWeek | I3: Notes | J3: LastUpdated | K3: TaskID
A4: Complete I-9 Employment Verification | B4: Sarah Mitchell | C4: sarah.mitchell@techcorp.com | D4: 14/04/2025 | E4: Open | F4: High | G4: Engineering | H4: 1 | I4: Documents submitted — awaiting HR sign-off | J4: 07/03/2025 | K4: TSK-001
A5: Set up company laptop and software | B5: Sarah Mitchell | C5: sarah.mitchell@techcorp.com | D5: 10/04/2025 | E5: Open | F5: High | G5: Engineering | H5: 1 | I5: IT ticket raised — laptop not yet collected | J5: 06/03/2025 | K5: TSK-002
A6: Enrol in company benefits portal | B6: Ravi Sharma | C6: ravi.sharma@techcorp.com | D6: 15/04/2025 | E6: Open | F6: Medium | G6: Marketing | H6: 1 | I6: Benefits guide sent by email on 01/03 | J6: 05/03/2025 | K6: TSK-003
A7: Complete mandatory GDPR training | B7: Ravi Sharma | C7: ravi.sharma@techcorp.com | D7: 08/03/2025 | E7: Open | F7: High | G7: Marketing | H7: 1 | I7: OVERDUE — follow up required immediately | J7: 01/03/2025 | K7: TSK-004
A8: Schedule 1-to-1 with line manager | B8: Liu Wei | C8: liu.wei@techcorp.com | D8: 18/04/2025 | E8: Open | F8: Medium | G8: Finance | H8: 2 | I8: Manager availability: Tuesday or Thursday afternoon | J8: 07/03/2025 | K8: TSK-005
A9: Sign employment contract addendum | B9: Amara Diallo | C9: amara.diallo@techcorp.com | D9: 07/03/2025 | E9: Open | F9: High | G9: HR | H9: 1 | I9: Due TODAY — contract in DocuSign inbox | J9: 04/03/2025 | K9: TSK-006
A10: Complete health & safety induction | B10: Amara Diallo | C10: amara.diallo@techcorp.com | D10: 21/04/2025 | E10: Open | F10: Medium | G10: HR | H10: 2 | I10: Book via facilities portal — 2hr session | J10: 07/03/2025 | K10: TSK-007
A11: Set up Slack and Teams accounts | B11: Tom Bradley | C11: tom.bradley@techcorp.com | D11: 11/04/2025 | E11: In Progress | F11: Medium | G11: Sales | H11: 1 | I11: IT in progress — ETA tomorrow | J11: 06/03/2025 | K11: TSK-008
A12: Attend company orientation session | B12: Tom Bradley | C12: tom.bradley@techcorp.com | D12: 14/04/2025 | E12: Open | F12: Low | G12: Sales | H12: 1 | I12: Next session: 14 April 2pm — calendar invite sent | J12: 07/03/2025 | K12: TSK-009
A13: Submit bank details for payroll | B13: Priya Nair | C13: priya.nair@techcorp.com | D13: 09/03/2025 | E13: Open | F13: High | G13: Marketing | H13: 1 | I13: Payroll cutoff is 10/03 — urgent | J13: 05/03/2025 | K13: TSK-010
A14: Complete diversity & inclusion training | B14: Priya Nair | C14: priya.nair@techcorp.com | D14: 22/04/2025 | E14: Open | F14: Low | G14: Marketing | H14: 2 | I14: Online module — approx 45 mins | J14: 07/03/2025 | K14: TSK-011
A15: Obtain building access pass | B15: James Okafor | C15: james.okafor@techcorp.com | D15: 12/04/2025 | E15: Open | F15: Medium | G15: Engineering | H15: 1 | I15: Photo ID required — bring passport to reception | J15: 07/03/2025 | K15: TSK-012
... A23: Complete probation review paperwork | B23: Maria Santos | C23: maria.santos@techcorp.com | D23: 30/04/2025 | E23: Open | F23: Medium | G23: HR | H23: 4 | I23: Manager to initiate review form 1 week before | J23: 07/03/2025 | K23: TSK-020
A24: TOTALS | D24: Open | E24: In Progress | F24: Complete | G24: High Priority | H24: Medium Priority | I24: Low Priority | J24: Total Tasks
D25: =COUNTIF(E4:E23,"Open") -> 17 | E25: =COUNTIF(E4:E23,"In Progress") -> 2 | F25: =COUNTIF(E4:E23,"Complete") -> 1 | G25: =COUNTIF(F4:F23,"High") -> 8 | H25: =COUNTIF(F4:F23,"Medium") -> 8 | I25: =COUNTIF(F4:F23,"Low") -> 4 | J25: =COUNTA(A4:A23) -> 20

Sheet Dashboard
A1: HR Onboarding Dashboard
A2: Live summary — automatically calculated from OnboardingTasks sheet
A4: Total Tasks | B4: Open | C4: In Progress | D4: Complete | E4: High Priority | F4: Due This Week
A5: =COUNTA(OnboardingTasks!A4:A23) -> 20 | B5: =COUNTIF(OnboardingTasks!E4:E23,"Open") -> 17 | C5: =COUNTIF(OnboardingTasks!E4:E23,"In Progress") -> 2 | D5: =COUNTIF(OnboardingTasks!E4:E23,"Complete") -> 1 | E5: =COUNTIF(OnboardingTasks!F4:F23,"High") -> 8 | F5: =COUNTIFS(OnboardingTasks!E4:E23,"Open",OnboardingTasks!D4:D23,"<="&TEXT(TODAY()+7,"DD/MM/YYYY")) -> 7
A8: Open Tasks by Department | E8: Open Tasks by Priority
A9: Engineering | B9: =COUNTIFS(OnboardingTasks!G4:G23,"Engineering",OnboardingTasks!E4:E23,"Open") -> 4 | C9: =IFERROR(B9/COUNTIF(OnboardingTasks!E4:E23,"Open"),0) -> 0.23529412 | E9: High | F9: =COUNTIFS(OnboardingTasks!F4:F23,"High",OnboardingTasks!E4:E23,"Open") -> 7
A10: Marketing | B10: =COUNTIFS(OnboardingTasks!G4:G23,"Marketing",OnboardingTasks!E4:E23,"Open") -> 4 | C10: =IFERROR(B10/COUNTIF(OnboardingTasks!E4:E23,"Open"),0) -> 0.23529412 | E10: Medium | F10: =COUNTIFS(OnboardingTasks!F4:F23,"Medium",OnboardingTasks!E4:E23,"Open") -> 6
A11: Finance | B11: =COUNTIFS(OnboardingTasks!G4:G23,"Finance",OnboardingTasks!E4:E23,"Open") -> 3 | C11: =IFERROR(B11/COUNTIF(OnboardingTasks!E4:E23,"Open"),0) -> 0.17647059 | E11: Low | F11: =COUNTIFS(OnboardingTasks!F4:F23,"Low",OnboardingTasks!E4:E23,"Open") -> 4
A12: HR | B12: =COUNTIFS(OnboardingTasks!G4:G23,"HR",OnboardingTasks!E4:E23,"Open") -> 4 | C12: =IFERROR(B12/COUNTIF(OnboardingTasks!E4:E23,"Open"),0) -> 0.23529412
A13: Sales | B13: =COUNTIFS(OnboardingTasks!G4:G23,"Sales",OnboardingTasks!E4:E23,"Open") -> 2 | C13: =IFERROR(B13/COUNTIF(OnboardingTasks!E4:E23,"Open"),0) -> 0.11764706
A16: Zapier Agent Configuration
A17: Spreadsheet Tab Name | B17: OnboardingTasks | C17: This exact name must be used in the Zapier Google Sheets step
A18: Filter Field | B18: Status | C18: Zapier filters on this column
A19: Filter Value | B19: Open | C19: Only rows with Status = Open are pulled
A20: Trigger Time | B20: 8:00 AM weekdays | C20: Set in Schedule by Zapier trigger
A21: AI Prompt Column Order | B21: TaskName, AssigneeName, DueDate, Priority, Department | C21: Formatter joins these into text block
A22: WhatsApp Format | B22: whatsapp:+[country code][number] | C22: e.g. whatsapp:+447700900123

Sheet ZapierGuide
A1: Quick Zapier Setup Reference
A2: Use this sheet alongside the step-by-step Zapier guide
A3: STEP | B3: ZAP STEP | C3: SETTING | D3: VALUE TO USE | E3: NOTES
A4: 1 | B4: Schedule Trigger | C4: Trigger type | D4: Every Day
A5: 1 | B5: Schedule Trigger | C5: Time of Day | D5: 8:00 AM | E5: Change to your preferred time
A6: 1 | B6: Schedule Trigger | C6: Days of Week | D6: Mon, Tue, Wed, Thu, Fri | E6: Uncheck Sat and Sun
A7: 2 | B7: Google Sheets | C7: Action Event | D7: Get Many Spreadsheet Rows | E7: NOT Get Spreadsheet Row
A8: 2 | B8: Google Sheets | C8: Worksheet | D8: OnboardingTasks | E8: Must match tab name exactly
A9: 2 | B9: Google Sheets | C9: Filter Field | D9: Status
A10: 2 | B10: Google Sheets | C10: Filter Value | D10: Open | E10: Capital O, no spaces
A11: 3 | B11: Filter by Zapier | C11: Condition | D11: TaskName — Exists | E11: Stops Zap if no open tasks
A12: 4 | B12: Formatter by Zapier | C12: Event | D12: Utilities
A13: 4 | B13: Formatter by Zapier | C13: Transform | D13: Line Itemizer | E13: Joins all tasks into one block
A14: 5 | B14: AI by Zapier | C14: Event | D14: Summarize Text
A15: 5 | B15: AI by Zapier | C15: Input | D15: Map Formatter output here | E15: Click lightning bolt to select
A16: 6 | B16: Gmail | C16: Body Type | D16: HTML | E16: Must be HTML not plain text
A17: 6 | B17: Gmail | C17: To | D17: hrmanager@yourcompany.com | E17: Replace with real email
A18: 7 | B18: Twilio | C18: Event | D18: Send WhatsApp Message
A19: 7 | B19: Twilio | C19: From | D19: whatsapp:+14155238886 | E19: Twilio sandbox number
A20: 7 | B20: Twilio | C20: To | D20: whatsapp:+[HR manager number] | E20: Include country code
